{
    "11726174-neo.nl@users.noreply.gitlab.com": "Neo",
    "11726174-neo.nomadic@users.noreply.gitlab.com": "Neo",
    "1718826-lykimquyen@users.noreply.gitlab.com": "lykimquyen",
    "1766551-zettez@users.noreply.gitlab.com": "Zettez",
    "2601505-prometheansacrifice@users.noreply.gitlab.com": "prometheansacrifice",
    "3097018+ManasJayanth@users.noreply.github.com": "Manas",
    "374817-mujx@users.noreply.gitlab.com": "mujx",
    "8037031-er433@users.noreply.gitlab.com": "E. Rivas",
    "946787-yrg@users.noreply.gitlab.com": "Yann Regis-Gianas",
    "Arthur Breitman": "Arthur Breitman",
    "David.Feuer@gmail.com": "David Feuer",
    "Richard.Bonichon@tweag.io": "Richard Bonichon",
    "a@b.c": "Arthur B",
    "adam.allombert@lambda-coins.com": "Adam Allombert-Goget",
    "adam.allombert@nomadic-labs.com": "Adam Allombert-Goget",
    "adrian@cryptium.io": "Adrian Brink",
    "ajinkya.raj@trili.tech": "Ajinkya Rajandekar",
    "al.schmitt@protonmail.com": "Anne-Laure",
    "alain.mebsout@functori.com": "Alain Mebsout",
    "alainmebsout@gmail.com": "Alain Mebsout",
    "albin.coquereau@nomadic-labs.com": "Albin Coquereau",
    "alex.krohg64@gmail.com": "Alex Krohg",
    "alex.kuprienko@tqtezos.com": "Alex Kuprienko",
    "alexandre.fmp.esteves@gmail.com": "Alexandre Esteves",
    "alfie@alfie.wtf": "Alfie John",
    "alistair.obrien@trili.tech": "Alistair O'Brien",
    "alvarillogp@gmail.com": "Alvaro",
    "alx@mit.edu": "Alex Coventry",
    "anastasia.courtney@trili.tech": "Anastasia Courtney",
    "andrea.cerone@trili.tech": "Andrea Cerone",
    "anne.laure@nomadic-labs.com": "Anne-Laure",
    "antoine.lanco@functori.com": "Antoine Lanco",
    "antonbachin@yahoo.com": "Anton Bachin",
    "antonio.locascio@nomadic-labs.com": "Antonio Locascio",
    "arnaud.bihan@functori.com": "arnaud",
    "arthur.breitman+nospam@tezos.com": "Arthur B",
    "arthur.breitman@gmail.com": "arthur.breitman@gmail.com",
    "arthurb": "Arthur Breitman",
    "arvid.jakobsson@nomadic-labs.com": "Arvid Jakobsson",
    "ashermanning@yahoo.co.uk": "Ash",
    "b@b.net": "b",
    "basile.pesin@gmail.com": "Basile Pesin",
    "be.danny.willems@gmail.com": "Danny Willems",
    "benjamin.canou@ocaml.pro": "Benjamin Canou",
    "benjamin@canou.fr": "Benjamin Canou",
    "benjamin@klakplok.net": "Benjamin Canou",
    "benjamin@ocamlpro.com": "Benjamin Canou",
    "bernardobruno@gmail.com": "bruno",
    "boubacar@nomadic-labs.com": "bsall",
    "bruno.bernardo@nomadic-labs.com": "Bruno B",
    "bruno.bernardo@tezos.com": "b",
    "bruno@nomadic-labs.com": "Bruno Bernardo",
    "bshanks.prog@gmail.com": "Bayle Shanks",
    "cagdas.bozman@ocamlpro.com": "Cagdas Bozman",
    "cauderlier@liafa.univ-paris-diderot.fr": "Raphael Cauderlier",
    "ch.martin@gmail.com": "Chris Martin",
    "charles.dehlinger@tezcore.com": "Charles Dehlinger",
    "charles.nguyen@nomadic-labs.com": "Charles Nguyen",
    "chiptus@gmail.com": "Chaim Lev-Ari",
    "chris_pinnock@mac.com": "Chris Pinnock",
    "clement.hurlin@tweag.io": "Cl\u00e9ment Hurlin",
    "clement@tarides.com": "Cl\u00e9ment Pascutto",
    "code@bnwr.net": "Rapha\u00ebl Proust",
    "colin.gonzalez@nomadic-labs.com": "Colin Gonz\u00e1lez",
    "contact@danny-willems.be": "Danny Willems",
    "contact@raphael-toledo.com": "Raphael Toledo",
    "contact@sagotch.fr": "Julien Sagot",
    "contact@tezos.com": "Tezos",
    "corentin.mehat@nomadic-labs.com": "Corentin M\u00e9hat",
    "corneliuhoffman@gmail.com": "Corneliu Hoffman",
    "craig@tarides.com": "Craig Ferguson",
    "d4hines@gmail.com": "Daniel Hines",
    "damiancoding@gmail.com": "damian",
    "dan.bornside@gmail.com": "Dan Bornside",
    "dan.bornside@obsidian.systems": "dbornside",
    "daniel.jean@nomadic-labs.com": "Daniel JEAN",
    "daniel@goldencube.info": "Daniel Hines",
    "daniel@lukenine45.net": "Daniel Smith",
    "dannygrove@bitgo.com": "Danny Grove",
    "david.dumas@tweag.io": "David Dumas",
    "davis.mil@husky.neu.edu": "Milo Davis",
    "dc@diogocastro.com": "Diogo Castro",
    "dev@clarus.me": "Guillaume Claret",
    "diana.savvatina@trili.tech": "Diana Savatina",
    "diane.gallois-wong@nomadic-labs.com": "Diane Gallois-Wong",
    "diane.galloiswong@gmail.com": "Diane Gallois-Wong",
    "dimitris.apostolou@icloud.com": "Dimitris Apostolou",
    "divesh.otwani@gmail.com": "Divesh Otwani",
    "dmirgaleev@mail.ru": "Dmitry Mir",
    "domninac@gmail.com": "icristescu",
    "doussot.alexandre@gmail.com": "Alexandre Doussot",
    "dzmitryi.rudkouski@altoros.com": "Dzmitryi Rudkouski",
    "eacameron@gmail.com": "Elliot Cameron",
    "edwin.ansari@lambda-coins.com": "Edwin Ansari",
    "eitan.chatav@gmail.com": "Eitan Chatav",
    "elric@imrryr.org": "Roland C. Dowdeswell",
    "emma.turner@trili.tech": "Emma Turner",
    "etienne.marais@nomadic-labs.com": "Etienne MARAIS",
    "etomknudsen@gmail.com": "Tom Knudsen",
    "eugen.zalinescu@gmail.com": "Eugen Zalinescu",
    "eugen.zalinescu@nomadic-labs.com": "Eugen Zalinescu",
    "eugen.zalinescu@tezcore.com": "Eugen Zalinescu",
    "eugen.zalinescu@tezos.com": "Eugen Zalinescu",
    "eugene.mishura@oxheadalpha.com": "Eugene Mishura",
    "evertedsphere@gmail.com": "Swann Moreau",
    "fabrice.le_fessant@ocamlpro.com": "Fabrice Le Fessant",
    "fardale+git@crans.org": "Fardale",
    "felix.puscasu@trili.tech": "Felix Puscasu",
    "fraifelipe@gmail.com": "Felipe Cardozo",
    "franci.dainese@gmail.com": "Karrq",
    "francois.thire@nomadic-labs.com": "Fran\u00e7ois Thir\u00e9",
    "fred@tarides.com": "Fr\u00e9d\u00e9ric Bour",
    "fredcy@gmail.com": "Fred Yankowski",
    "frej.soya@ext.nomadic-labs.com": "Frej Soya",
    "gabriel.alfour@gmail.com": "Gabriel Alfour",
    "gabriel.moise@trili.tech": "Gabriel Moise",
    "gauthier.sebille@gmail.com": "Gauthier SEBILLE",
    "gauthier@marigold.dev": "Gauthier SEBILLE",
    "gb.fefe@protonmail.com": "G.B. Fefe",
    "gbikal@gmail.com": "Bikal Gurung",
    "georges.duperon@nomadic-labs.com": "Georges Dup\u00e9ron",
    "georges.duperon@tezcore.com": "Georges Dup\u00e9ron",
    "german@nomadic-labs.com": "Germ\u00e1n Delbianco",
    "gessadavide@gmail.com": "Davide Gessa",
    "gie1994@gmail.com": "Ivan Gromakovskii",
    "github@joachim-ansorg.de": "jansorg",
    "github@matthewboehm.com": "utdrmac",
    "gitlab@hnr.gr": "Gr\u00e9goire Henry",
    "goldencube@protonmail.com": "Daniel Hines",
    "greg@hnr.gr": "Gr\u00e9goire",
    "gregoire.henry@ocaml.pro": "Gr\u00e9goire Henry",
    "gregoire.henry@ocamlpro.com": "Gr\u00e9goire Henry",
    "gregoire.henry@tezos.com": "Gr\u00e9goire Henry",
    "gst@gst.name": "Guenther Starnberger",
    "guillaume.bau@nomadic-labs.com": "Guillaume Bau",
    "guillaume.bau@tezcore.com": "baugr",
    "guillem.rieu@luminar.fr": "Guillem Rieu",
    "hai.nguyenvan.phie@gmail.com": "Hai Nguyen Van",
    "hai@nomadic-labs.com": "Hai Nguyen Van",
    "hans.hoglund@trili.tech": "Hans Hoglund",
    "hantang.sun@trili.tech": "Hantang Sun",
    "haochenx@acm.org": "Haochen Xie",
    "hiromasa.saito@dailambda.jp": "taiseiKMC",
    "hugo.heuzard@gmail.com": "Hugo Heuzard",
    "hugo.heuzard@lambda-coins.com": "Hugo Heuzard",
    "hugo.heuzard@nomadic-labs.com": "Hugo Heuzard",
    "i@yoichihirai.com": "Yoichi Hirai",
    "iguer.pro@gmail.com": "OCamlPro-Iguernlala",
    "iguer@functori.com": "iguerNL@Functori",
    "ilias.garnier@nomadic-labs.com": "Ilias Garnier",
    "ilias.garnier@tezcore.com": "Ilias",
    "ilya.peresadin@trili.tech": "Ilya Peresadin",
    "info@lazaridis.com": "Lazaridis",
    "ioana@tarides.com": "icristescu",
    "jacquin.mininger@gmail.com": "Jacquin Mininger",
    "jacquin.mininger@obsidian.systems": "Jacquin Mininger",
    "jaiyalas@gmail.com": "YY",
    "james.deikun@obsidian.systems": "James Deikun",
    "james.p.edwards42@gmail.com": "James Edwards",
    "jamie@nomadic-labs.com": "Jamie @ Nomadic",
    "jason@ridgway-taylor.co.uk": "Jason Ridgway-Taylor",
    "jeremie.goldberg@nomadic-labs.com": "J\u00e9r\u00e9mie Goldberg",
    "jerome.chailloux@tezcore.com": "Jerome Chailloux",
    "jev@ecadlabs.com": "Jev Bj\u00f6rsell",
    "joaosreis@outlook.pt": "Jo\u00e3o Santos Reis",
    "joel.bjornson@gmail.com": "Joel Bjornson",
    "joel.bjornson@trili.tech": "Joel Bjornson",
    "johann@tulip.toos": "Johann",
    "jon@e.rroneo.us": "Jonathan",
    "jswbae@gmail.com": "Jeremy Bae",
    "jtcoolen@pm.me": "Julien Coolen",
    "jules.viennot@nomadic-labs.com": "Jules Viennot",
    "julien.coolen@nomadic-labs.com": "Julien Coolen",
    "julien.debon@tweag.io": "Julien Debon",
    "julien.rolland@nomadic-labs.com": "Julien Rolland",
    "julien.sagot@lambda-coins.com": "Julien Sagot",
    "julien.tesson@nomadic-labs.com": "Julien Tesson",
    "julien.tesson@tezcore.com": "Julien Tesson",
    "jun.furuse@dailambda.jp": "Jun Furuse",
    "jun.furuse@gmail.com": "Jun Furuse",
    "justin@starkandwayne.com": "Justin Carter",
    "kazuhiro.kobayashi@dailambda.jp": "KOBAYASHI Kazuhiro",
    "keefer.t@gmail.com": "Keefer Taylor",
    "keefer@keefertaylor.com": "Keefer Taylor",
    "killian.delarue@gmail.com": "Killian Delarue",
    "killian.delarue@nomadic-labs.com": "Killian Delarue",
    "killian@nomadic-labs.com": "Killian Delarue",
    "kim-quyen.ly@nomadic-labs.com": "Ly Kim Quyen",
    "kim-quyen.ly@tezcore.com": "L\u00fd Kim Quy\u00ean",
    "kim.quyen.ly@tezos.com": "Quyen",
    "king_sash@yahoo.de": "Blindripper",
    "kirelagin@gmail.com": "Kirill Elagin",
    "kumar.shubham.off@gmail.com": "Shubham Kumar",
    "lacramioara.astefanoaei@nomadic-labs.com": "Lacramioara Astefanoaei",
    "lacramioara.astefanoaei@tezcore.com": "astefano",
    "linoshitani@gmail.com": "lin",
    "litchi.pi@protonmail.com": "Litchi Pi",
    "locascio.Antonio@nomadic-labs.com": "Antonio Locascio",
    "lthms@nomadic-labs.com": "Thomas Letan",
    "lucas.randazzo@nomadic-labs.com": "Lucas Randazzo",
    "lucas@nomadic-labs.com": "Lucas Randazzo",
    "luciano.freitas@lambda-coins.com": "Luciano Freitas",
    "ly.kim.quyen@ens.fr": "L\u00fd Kim Quy\u00ean",
    "lykimq@gmail.com": "lykimq",
    "mac.ambrona@gmail.com": "ambrona",
    "mail@dbrgn.ch": "Danilo Bargen",
    "mail@ja-dev.eu": "Joachim Ansorg",
    "marc.beunardeau@nomadic-labs.com": "marcbeunardeau",
    "marcin.pastudzki@gmail.com": "Marcin Pastudzki",
    "marcin.pastudzki@tqtezos.com": "Marcin Pastudzki",
    "marco@stronati.org": "Marco Stronati",
    "marge-bot-google-group@lambda-coins.com": "Marge Bot",
    "marge-bot@nomadic-labs.com": "Marge Bot",
    "marina.polubelova@nomadic-labs.com": "Marina Polubelova",
    "markkarpov92@gmail.com": "Mark Karpov",
    "martin.tomazic97@gmail.com": "Martin Tomazic",
    "martoon.hsk@gmail.com": "martoon",
    "mathias.bourgoin@gmail.com": "MBourgoin",
    "mathias.bourgoin@nomadic-labs.com": "mbourgoin",
    "mathias.bourgoin@tezcore.com": "MBourgoin",
    "matsak.i.v@gmail.com": "Igor Matsak",
    "matt.g.d.walker@gmail.com": "Matt Walker",
    "mattias@kojin.tech": "mattiasdrp",
    "maxime.levillain@functori.com": "Maxime Levillain",
    "me@craigfe.io": "Craig Ferguson",
    "me@hkjn.me": "Henrik Jonsson",
    "me@robinbb.com": "Robin Bate Boerop",
    "mehdi.bouaziz@nomadic-labs.com": "Mehdi Bouaziz",
    "metanivek@gmail.com": "metanivek",
    "michael.laporte@ocamlpro.com": "michael",
    "michael.zaikin@trili.tech": "Michael Zaikin",
    "micsproul@gmail.com": "Michael Sproul",
    "mjbauer95@gmail.com": "Matthew Bauer",
    "mk@baking-bad.org": "Maxim Kucherov",
    "mohamed.iguernelala@ocaml.pro": "Mohamed Iguernlala",
    "mohamed.iguernlala@ocamlpro.com": "OCamlPro-Iguernlala",
    "moremi.vannak@serokell.io": "Moremi Vannak",
    "mthl@reuz.fr": "Mathieu Lirzin",
    "mujx@tuta.io": "mujx",
    "nathan.p.rebours@gmail.com": "Nathan Rebours",
    "ngoguey42@free.fr": "ngoguey42",
    "ngoguey@student.42.fr": "Ngoguey42",
    "nic.volanschi@nomadic-labs.com": "Nic Volanschi",
    "nicolas.ayache@nomadic-labs.com": "Nicolas Ayache",
    "nicolas.bacquey@tweag.io": "Nicolas BACQUEY",
    "nicolas.bacquey@yahoo.fr": "Nicolas BACQUEY",
    "nicolas.ochem@gmail.com": "Nicolas Ochem",
    "nicolas.pinto@gmail.com": "Nicolas Pinto",
    "nicolas.raymond@nomadic-labs.com": "nraymond",
    "nohmane.oulali+marge@lambda-coins.com": "Marge Bot",
    "nohmane.oulali@lambda-coins.com": "Neo",
    "novalis@novalis.org": "David Turner",
    "ole.kruger@trili.tech": "Ole Kr\u00fcger",
    "oliver@blockwatch.cc": "Oliver Simon",
    "ovidiu@pointfree.ro": "Ovidiu Deac",
    "p.khrystenko@gmail.com": "Pavlo Khrystenko",
    "pasqu4le@gmail.com": "pasqu4le",
    "paul.laforgue@nomadic-labs.com": "phink",
    "paul.laforgue@tezcore.com": "Paul Laforgue",
    "pe.cornilleau@marigold.dev": "pecornilleau",
    "peter.duchovni@nomadic-labs.com": "Peter Duchovni",
    "peter.duchovni@tqtezos.com": "Peter Duchovni",
    "philippe.bidinger@nomadic-labs.com": "Philippe B",
    "philippe.bidinger@tezcore.com": "Philippe Bidinger",
    "philippe.wang@gmail.com": "Philippe Wang",
    "philippe.wang@nomadic-labs.com": "Philippe Wang",
    "pierre-emmanuel.cornilleau@lambda-coins.com": "Pierre-Emmanuel Cornilleau",
    "pierre.boutillier@ens-lyon.org": "Pierre Boutillier",
    "pierre.boutillier@laposte.net": "Pierre Boutillier",
    "pierre.boutillier@nomadic-labs.com": "Pierre Boutillier",
    "pierre.chambart@ocamlpro.com": "Pierre Chambart",
    "pierrelouis.dubois@tutanota.com": "Pierre-Louis",
    "pierrick.couderc@nomadic-labs.com": "Pierrick Couderc",
    "pierrick@thrim.me": "Pierrick Couderc",
    "pietro.abate@inria.fr": "Pietro",
    "pietro.abate@nomadic-labs.com": "Pietro Abate",
    "pietro.abate@pps.univ-paris-diderot.fr": "Pietro Abate",
    "pietro.abate@tezcore.com": "Pietro",
    "pro.acoquer@protonmail.com": "Albin Coquereau",
    "quyen@marigold.dev": "lykimquyen",
    "r.alex.stokes@gmail.com": "Alex Stokes",
    "raphael.cauderlier@nomadic-labs.com": "Rapha\u00ebl Cauderlier",
    "rbozman.functori@gmail.com": "Rodi-Can Bozman",
    "remy.el-sibaie@nomadic-labs.com": "R\u00e9my El Siba\u00efe",
    "remy@nomadic-labs.com": "R\u00e9my El Siba\u00efe",
    "rich@ayottesoftware.com": "Richard Ayotte",
    "richard.bonichon@gmail.com": "Richard Bonichon",
    "richard.bonichon@nomadic-labs.com": "Richard Bonichon",
    "richard.bonichon@tweag.io": "Richard Bonichon",
    "richardneildavison@gmail.com": "Richard Davison",
    "robpub@google.com": "Rob Witoff",
    "rodi.bozman@functori.com": "Rodi-Can Bozman",
    "rodrigo_quelhas@outlook.pt": "Rodrigo Quelhas",
    "romain@nomadic-labs.com": "Romain Bardou",
    "roman.melnikov@serokell.io": "Roman Melnikov",
    "root@livid.pp.ru": "Nikolay Yakimov",
    "rozovyk.arte@gmail.com": "Rozovyk Artemiy",
    "rozovyk.artem@gmail.com": "Artemiy",
    "rueshyna@gmail.com": "ChiaChi Tsai",
    "ryan.tan@trili.tech": "Ryan Tan",
    "ryan@loomba.io": "Ryan Loomba",
    "sandeep.chandrika@serokell.io": "Sandeep.C.R",
    "scott.scites@railcar88.com": "Scott Scites",
    "seb@mondet.org": "Sebastien Mondet",
    "sebastien.palmer@functori.com": "S\u00e9bastien Palmer",
    "sheremetyev@gmail.com": "Fedor Sheremetyev",
    "siderisk@auth.gr": "Konstantinos Sideris",
    "sol.lederer@gmail.com": "sol.lederer",
    "solomon.lederer@ext.nomadic-labs.com": "Solomon Lederer",
    "sophiagoldnyc@gmail.com": "Sophia Gold",
    "sota.sato@dailambda.jp": "Sota Sato",
    "ssigo1529@gmail.com": "satos",
    "steve.sanches@nomadic-labs.com": "pikatos",
    "steve@sanityinc.com": "Steve Purcell",
    "svantimir@gmail.com": "Sventimir",
    "sylvain.ribstein@gmail.com": "Sylvain Ribstein",
    "sylvain.ribstein@nomadic-labs.com": "Sylvain Ribstein",
    "syogo8118@yahoo.co.jp": "satos---jp",
    "taisei@kmc.gr.jp": "taiseiKMC",
    "theeduardorfs@gmail.com": "EduardoRFS",
    "thomas.athorne@trili.tech": "Thomas Athorne",
    "thomas.blanc@ocamlpro.com": "Thomas Blanc",
    "thomas.pecseli@trili.tech": "Thomas P\u00e9cseli",
    "thomas@gazagnaire.org": "Thomas Gazagnaire",
    "timothymcmackin@yahoo.com": "Tim McMackin",
    "tom@tomjack.co": "Tom Jack",
    "tomas@cryptium.ch": "Tom\u00e1\u0161 Zemanovi\u010d",
    "tzemanovic@gmail.com": "Tom\u00e1\u0161 Zemanovi\u010d",
    "ulrik.strid@outlook.com": "Ulrik Strid",
    "utizoc@gmail.com": "Bruno Deferrari",
    "v.dumitrescu@outlook.com": "Victor Dumitrescu",
    "valentin.chaboche@nomadic-labs.com": "Valentin Chaboche",
    "vb@luminar.eu.org": "Vincent Bernardoff",
    "venator@luminar.fr": "venator",
    "victor.allombert@nomadic-labs.com": "Victor Allombert",
    "victor.allombert@tezcore.com": "Victor Allombert",
    "victor.dumitrescu@nomadic-labs.com": "Victor Dumitrescu",
    "vincent.botbol@gmail.com": "Vincent Botbol",
    "vincent.botbol@nomadic-labs.com": "vbot",
    "vincent.botbol@tezcore.com": "Vincent Botbol",
    "vivien.pelletier@nomadic-labs.com": "Vivien",
    "wyatts+github@gmail.com": "Wyatt Sullivan",
    "xavier.vdw@gmail.com": "xvw",
    "xf@marigold.dev": "X",
    "y.imai@proof-ninja.co.jp": "Yoshihiro Imai",
    "yann@nomadic-labs.com": "Yann Regis-Gianas",
    "yoshihiro503@proofcafe.org": "yoshihiro503",
    "yves.coriton@sword-group.com": "Yves Coriton",
    "zachshipko@gmail.com": "zach",
    "zaynah.dargaye@nomadic-labs.com": "Zaynah Dargaye",
    "zhenya1007@gmail.com": "Zhenya Roubinchtein",
    "ztepler@gmail.com": "Stepan Naumov"
}